avance1/Muxdenrrutamiento/Mux2a1_destEst.v
/* Generated by Yosys 0.7 (git sha1 61f6811, gcc 6.2.0-11ubuntu1 -O2 -fdebug-prefix-map=/build/yosys-OIL3SR/yosys-0.7=. -fstack-protector-strong -fPIC -Os) */

(* top =  1  *)
(* src = "Mux2a1_dest.v:1" *)
module mux2a1dest_est(pop0, pop1, datain_dest0, datain_dest1, reset_L, validoutdest, dataout_dest);
  wire _000_;
  wire _001_;
  wire _002_;
  wire _003_;
  wire _004_;
  wire _005_;
  wire _006_;
  wire _007_;
  wire _008_;
  wire _009_;
  wire _010_;
  wire _011_;
  wire _012_;
  wire _013_;
  wire _014_;
  wire _015_;
  wire _016_;
  wire _017_;
  wire _018_;
  wire _019_;
  wire _020_;
  wire _021_;
  wire _022_;
  wire _023_;
  wire _024_;
  wire _025_;
  wire _026_;
  wire _027_;
  wire _028_;
  wire _029_;
  wire _030_;
  wire _031_;
  wire _032_;
  wire _033_;
  wire _034_;
  wire _035_;
  wire _036_;
  wire _037_;
  wire _038_;
  wire _039_;
  wire _040_;
  wire _041_;
  wire _042_;
  wire _043_;
  wire _044_;
  wire _045_;
  wire _046_;
  wire _047_;
  wire _048_;
  wire _049_;
  wire _050_;
  wire _051_;
  wire _052_;
  wire _053_;
  (* src = "Mux2a1_dest.v:5" *)
  input [9:0] datain_dest0;
  (* src = "Mux2a1_dest.v:6" *)
  input [9:0] datain_dest1;
  (* src = "Mux2a1_dest.v:10" *)
  output [9:0] dataout_dest;
  (* src = "Mux2a1_dest.v:3" *)
  input pop0;
  (* src = "Mux2a1_dest.v:4" *)
  input pop1;
  (* src = "Mux2a1_dest.v:7" *)
  input reset_L;
  (* src = "Mux2a1_dest.v:9" *)
  output validoutdest;
  NOT _054_ (
    .A(reset_L),
    .Y(_000_)
  );
  NOT _055_ (
    .A(datain_dest1[0]),
    .Y(_001_)
  );
  NOT _056_ (
    .A(pop0),
    .Y(_002_)
  );
  NAND _057_ (
    .A(pop1),
    .B(_002_),
    .Y(_003_)
  );
  NOR _058_ (
    .A(_003_),
    .B(_001_),
    .Y(_004_)
  );
  NOT _059_ (
    .A(datain_dest0[0]),
    .Y(_005_)
  );
  NOR _060_ (
    .A(_005_),
    .B(_002_),
    .Y(_006_)
  );
  NOR _061_ (
    .A(_006_),
    .B(_004_),
    .Y(_007_)
  );
  NOR _062_ (
    .A(_007_),
    .B(_000_),
    .Y(dataout_dest[0])
  );
  NOT _063_ (
    .A(datain_dest1[1]),
    .Y(_008_)
  );
  NOR _064_ (
    .A(_003_),
    .B(_008_),
    .Y(_009_)
  );
  NOT _065_ (
    .A(datain_dest0[1]),
    .Y(_010_)
  );
  NOR _066_ (
    .A(_010_),
    .B(_002_),
    .Y(_011_)
  );
  NOR _067_ (
    .A(_011_),
    .B(_009_),
    .Y(_012_)
  );
  NOR _068_ (
    .A(_012_),
    .B(_000_),
    .Y(dataout_dest[1])
  );
  NOT _069_ (
    .A(datain_dest1[2]),
    .Y(_013_)
  );
  NOR _070_ (
    .A(_003_),
    .B(_013_),
    .Y(_014_)
  );
  NOT _071_ (
    .A(datain_dest0[2]),
    .Y(_015_)
  );
  NOR _072_ (
    .A(_015_),
    .B(_002_),
    .Y(_016_)
  );
  NOR _073_ (
    .A(_016_),
    .B(_014_),
    .Y(_017_)
  );
  NOR _074_ (
    .A(_017_),
    .B(_000_),
    .Y(dataout_dest[2])
  );
  NOT _075_ (
    .A(datain_dest1[3]),
    .Y(_018_)
  );
  NOR _076_ (
    .A(_003_),
    .B(_018_),
    .Y(_019_)
  );
  NOT _077_ (
    .A(datain_dest0[3]),
    .Y(_020_)
  );
  NOR _078_ (
    .A(_020_),
    .B(_002_),
    .Y(_021_)
  );
  NOR _079_ (
    .A(_021_),
    .B(_019_),
    .Y(_022_)
  );
  NOR _080_ (
    .A(_022_),
    .B(_000_),
    .Y(dataout_dest[3])
  );
  NOT _081_ (
    .A(datain_dest1[4]),
    .Y(_023_)
  );
  NOR _082_ (
    .A(_003_),
    .B(_023_),
    .Y(_024_)
  );
  NOT _083_ (
    .A(datain_dest0[4]),
    .Y(_025_)
  );
  NOR _084_ (
    .A(_025_),
    .B(_002_),
    .Y(_026_)
  );
  NOR _085_ (
    .A(_026_),
    .B(_024_),
    .Y(_027_)
  );
  NOR _086_ (
    .A(_027_),
    .B(_000_),
    .Y(dataout_dest[4])
  );
  NOT _087_ (
    .A(datain_dest1[5]),
    .Y(_028_)
  );
  NOR _088_ (
    .A(_003_),
    .B(_028_),
    .Y(_029_)
  );
  NOT _089_ (
    .A(datain_dest0[5]),
    .Y(_030_)
  );
  NOR _090_ (
    .A(_030_),
    .B(_002_),
    .Y(_031_)
  );
  NOR _091_ (
    .A(_031_),
    .B(_029_),
    .Y(_032_)
  );
  NOR _092_ (
    .A(_032_),
    .B(_000_),
    .Y(dataout_dest[5])
  );
  NOT _093_ (
    .A(datain_dest1[6]),
    .Y(_033_)
  );
  NOR _094_ (
    .A(_003_),
    .B(_033_),
    .Y(_034_)
  );
  NOT _095_ (
    .A(datain_dest0[6]),
    .Y(_035_)
  );
  NOR _096_ (
    .A(_035_),
    .B(_002_),
    .Y(_036_)
  );
  NOR _097_ (
    .A(_036_),
    .B(_034_),
    .Y(_037_)
  );
  NOR _098_ (
    .A(_037_),
    .B(_000_),
    .Y(dataout_dest[6])
  );
  NOT _099_ (
    .A(datain_dest1[7]),
    .Y(_038_)
  );
  NOR _100_ (
    .A(_003_),
    .B(_038_),
    .Y(_039_)
  );
  NOT _101_ (
    .A(datain_dest0[7]),
    .Y(_040_)
  );
  NOR _102_ (
    .A(_040_),
    .B(_002_),
    .Y(_041_)
  );
  NOR _103_ (
    .A(_041_),
    .B(_039_),
    .Y(_042_)
  );
  NOR _104_ (
    .A(_042_),
    .B(_000_),
    .Y(dataout_dest[7])
  );
  NOT _105_ (
    .A(datain_dest1[8]),
    .Y(_043_)
  );
  NOR _106_ (
    .A(_003_),
    .B(_043_),
    .Y(_044_)
  );
  NOT _107_ (
    .A(datain_dest0[8]),
    .Y(_045_)
  );
  NOR _108_ (
    .A(_045_),
    .B(_002_),
    .Y(_046_)
  );
  NOR _109_ (
    .A(_046_),
    .B(_044_),
    .Y(_047_)
  );
  NOR _110_ (
    .A(_047_),
    .B(_000_),
    .Y(dataout_dest[8])
  );
  NOT _111_ (
    .A(datain_dest1[9]),
    .Y(_048_)
  );
  NOR _112_ (
    .A(_003_),
    .B(_048_),
    .Y(_049_)
  );
  NOT _113_ (
    .A(datain_dest0[9]),
    .Y(_050_)
  );
  NOR _114_ (
    .A(_050_),
    .B(_002_),
    .Y(_051_)
  );
  NOR _115_ (
    .A(_051_),
    .B(_049_),
    .Y(_052_)
  );
  NOR _116_ (
    .A(_052_),
    .B(_000_),
    .Y(dataout_dest[9])
  );
  NOR _117_ (
    .A(pop1),
    .B(pop0),
    .Y(_053_)
  );
  NOR _118_ (
    .A(_053_),
    .B(_000_),
    .Y(validoutdest)
  );
endmodule

avance1/Muxdenrrutamiento/Mux2a1_dest.v
module mux2a1dest_cond(
    //entradas
    input pop0,//valid0 y prioridad absoluta para este
    input pop1,//valid1 y prioridad baja
    input [9:0] datain_dest0,
    input [9:0] datain_dest1,
    input reset_L,
    //salidas
    output reg validoutdest,
    output reg [9:0] dataout_dest
    );
    reg [9:0] temp;
    reg validtemp;
    always @ (*) begin
        temp = 10'b0;
        validtemp = 0;
        if(pop0 == 1 && pop1 == 0) begin
            validtemp = pop0;
            temp = datain_dest0;
        end
        else if(pop0 == 0 && pop1 == 1) begin
            validtemp = pop1;
            temp = datain_dest1;
        end
        else if(pop0 == 1 && pop1 == 1) begin
            validtemp = pop0;
            temp = datain_dest0;
        end
        else begin
            validtemp = 0;
            temp = 10'b0;
        end   
    end
    always @ (*) begin
        if(!reset_L) begin
            dataout_dest <= 10'b0;
            validoutdest <= 0;
        end
        else begin
            dataout_dest <= temp;
            validoutdest <= validtemp;
        end
    end
endmodule

avance1/Muxdenrrutamiento/probadormux_dest.v
module probadordest(
    //salidas
    output reg pop0,
    output reg pop1,
    output reg [9:0] datain_dest0,
    output reg [9:0] datain_dest1,
    output reg reset_L,
    output reg clk,
    //entradas mux dest
    input validoutdest,
    input [9:0] dataout_dest,
    //entradas Est
    input validoutdestEst,
    input [9:0] dataout_destEst  
    );
    initial begin
        $dumpfile("mux2a1_dest.vcd");
        $dumpvars;
        pop0 <= 0;
        pop1 <= 0;
        datain_dest0 <= 10'b0;
        datain_dest1 <= 10'b0;
        reset_L <= 0;
        @(posedge clk);
        reset_L <= 1;
        @(posedge clk);
        pop0 <= 1;
        datain_dest0 <= 1011011010;
        datain_dest1 <= 1101011010;
        @(posedge clk);
        pop0 <= 0;
        pop1 <= 1;
        datain_dest0 <= 1011101011;
        datain_dest1 <= 1011010110;
        @(posedge clk);
        pop0 <= 1;
        pop1 <= 0;
        datain_dest0 <= 0110101110;
        datain_dest1 <= 1011101001;
        @(posedge clk);
        pop0 <= 0;
        pop1 <= 1;
        datain_dest0 <= 1110101101;
        datain_dest1 <= 1001011011;
        @(posedge clk);
        pop0 <= 0;
        pop1 <= 0;
        datain_dest0 <= 1011101010;
        datain_dest1 <= 1011010110;
        @(posedge clk);
        datain_dest0 <= 1011011010;
        datain_dest1 <= 1111011010;
        @(posedge clk);
        datain_dest0 <= 1010100101;
        datain_dest1 <= 1111010000;
        @(posedge clk);
        datain_dest0 <= 1010010110;
        datain_dest1 <= 0001010010;
        @(posedge clk);
        pop0 <= 1;
        pop1 <= 1;
        datain_dest0 <= 1011010110;
        datain_dest1 <= 1001010110;
        @(posedge clk);
        datain_dest0 <= 1101110010;
        datain_dest1 <= 1011101010;
        @(posedge clk);
        datain_dest0 <= 1011010101;
        datain_dest1 <= 1011010110;
        @(posedge clk);
        pop0 <= 0;
        @(posedge clk);
        datain_dest1 <= 1111111111;
        repeat (2) begin
            @(posedge clk);
        end
		$finish;
    end
    // Reloj
	initial	clk <= 0;
	always	#100 clk <= ~clk;
endmodule

avance1/Muxdenrrutamiento/Bancopruebas.v
`timescale 	1ns	/ 100ps
`include "Mux2a1_dest.v"
`include "probadormux_dest.v" 
`include "cmos_cells.v" 
`include "Mux2a1_destEst.v" 

module BancoPruebas;
    wire pop0, pop1, validoutdest, reset_L, clk, validoutdestEst;
    wire [9:0] datain_dest0, datain_dest1, dataout_dest, dataout_destEst;
    probadordest proba(
                    //salidas
                    .pop0 (pop0),
                    .pop1 (pop1),
                    .datain_dest0 (datain_dest0[9:0]),
                    .datain_dest1 (datain_dest1[9:0]),
                    .reset_L (reset_L),
                    .clk (clk),
                    //entradas
                    .validoutdest (validoutdest),
                    .dataout_dest (dataout_dest),
                    .validoutdestEst (validoutdestEst),
                    .dataout_destEst (dataout_destEst)
    );
    mux2a1dest_cond muxdest(
                    //salidas
                    .validoutdest (validoutdest),
                    .dataout_dest (dataout_dest[9:0]),
                    //entradas
                    .pop0 (pop0),
                    .pop1 (pop1),
                    .datain_dest0 (datain_dest0[9:0]),
                    .datain_dest1 (datain_dest1[9:0]),
                    .reset_L (reset_L)
    );
    mux2a1dest_est muxestEst(
                    //salidas
                    .validoutdest (validoutdestEst),
                    .dataout_dest (dataout_destEst[9:0]),
                    //entradas
                    .pop0 (pop0),
                    .pop1 (pop1),
                    .datain_dest0 (datain_dest0[9:0]),
                    .datain_dest1 (datain_dest1[9:0]),
                    .reset_L (reset_L)
    );
    
endmodule

avance1/Demuxdenrrutamiento/cmos_cells.v
module BUF(A, Y);
input A;
output Y;
assign Y = A;
endmodule

module NOT (A, Y);
input A;
output Y;
assign  Y = ~A;
endmodule

module NAND(A, B, Y);
input A, B;
output Y;
assign  Y = ~(A & B);
endmodule

module NOR(A, B, Y);
input A, B;
output Y;
assign  Y = ~(A | B);
endmodule

module DFF(C, D, Q);
input C, D;
output reg Q;
always @(posedge C)
	Q <= D;
endmodule

module DFFSR(C, D, Q, S, R);
input C, D, S, R;
output reg Q;
always @(posedge C, posedge S, posedge R)
	if (S)
		Q <= 1'b1;
	else if (R)
		Q <= 1'b0;
	else
		Q <= D;
endmodule

avance1/Muxdenrrutamiento/mux2a1_dest.vcd
$date
	Wed Jun 17 06:07:20 2020
$end
$version
	Icarus Verilog
$end
$timescale
	100ps
$end
$scope module BUF $end
$var wire 1 ! A $end
$var wire 1 " Y $end
$upscope $end
$scope module BancoPruebas $end
$var wire 1 # validoutdestEst $end
$var wire 1 $ validoutdest $end
$var wire 1 % reset_L $end
$var wire 1 & pop1 $end
$var wire 1 ' pop0 $end
$var wire 10 ( dataout_destEst [9:0] $end
$var wire 10 ) dataout_dest [9:0] $end
$var wire 10 * datain_dest1 [9:0] $end
$var wire 10 + datain_dest0 [9:0] $end
$var wire 1 , clk $end
$scope module muxdest $end
$var wire 1 % reset_L $end
$var wire 1 & pop1 $end
$var wire 1 ' pop0 $end
$var wire 10 - datain_dest1 [9:0] $end
$var wire 10 . datain_dest0 [9:0] $end
$var reg 10 / dataout_dest [9:0] $end
$var reg 10 0 temp [9:0] $end
$var reg 1 $ validoutdest $end
$var reg 1 1 validtemp $end
$upscope $end
$scope module muxestEst $end
$var wire 1 # validoutdest $end
$var wire 1 % reset_L $end
$var wire 1 & pop1 $end
$var wire 1 ' pop0 $end
$var wire 10 2 dataout_dest [9:0] $end
$var wire 10 3 datain_dest1 [9:0] $end
$var wire 10 4 datain_dest0 [9:0] $end
$var wire 1 5 _053_ $end
$var wire 1 6 _052_ $end
$var wire 1 7 _051_ $end
$var wire 1 8 _050_ $end
$var wire 1 9 _049_ $end
$var wire 1 : _048_ $end
$var wire 1 ; _047_ $end
$var wire 1 < _046_ $end
$var wire 1 = _045_ $end
$var wire 1 > _044_ $end
$var wire 1 ? _043_ $end
$var wire 1 @ _042_ $end
$var wire 1 A _041_ $end
$var wire 1 B _040_ $end
$var wire 1 C _039_ $end
$var wire 1 D _038_ $end
$var wire 1 E _037_ $end
$var wire 1 F _036_ $end
$var wire 1 G _035_ $end
$var wire 1 H _034_ $end
$var wire 1 I _033_ $end
$var wire 1 J _032_ $end
$var wire 1 K _031_ $end
$var wire 1 L _030_ $end
$var wire 1 M _029_ $end
$var wire 1 N _028_ $end
$var wire 1 O _027_ $end
$var wire 1 P _026_ $end
$var wire 1 Q _025_ $end
$var wire 1 R _024_ $end
$var wire 1 S _023_ $end
$var wire 1 T _022_ $end
$var wire 1 U _021_ $end
$var wire 1 V _020_ $end
$var wire 1 W _019_ $end
$var wire 1 X _018_ $end
$var wire 1 Y _017_ $end
$var wire 1 Z _016_ $end
$var wire 1 [ _015_ $end
$var wire 1 \ _014_ $end
$var wire 1 ] _013_ $end
$var wire 1 ^ _012_ $end
$var wire 1 _ _011_ $end
$var wire 1 ` _010_ $end
$var wire 1 a _009_ $end
$var wire 1 b _008_ $end
$var wire 1 c _007_ $end
$var wire 1 d _006_ $end
$var wire 1 e _005_ $end
$var wire 1 f _004_ $end
$var wire 1 g _003_ $end
$var wire 1 h _002_ $end
$var wire 1 i _001_ $end
$var wire 1 j _000_ $end
$scope module _054_ $end
$var wire 1 j Y $end
$var wire 1 % A $end
$upscope $end
$scope module _055_ $end
$var wire 1 k A $end
$var wire 1 i Y $end
$upscope $end
$scope module _056_ $end
$var wire 1 h Y $end
$var wire 1 ' A $end
$upscope $end
$scope module _057_ $end
$var wire 1 h B $end
$var wire 1 g Y $end
$var wire 1 & A $end
$upscope $end
$scope module _058_ $end
$var wire 1 g A $end
$var wire 1 i B $end
$var wire 1 f Y $end
$upscope $end
$scope module _059_ $end
$var wire 1 l A $end
$var wire 1 e Y $end
$upscope $end
$scope module _060_ $end
$var wire 1 e A $end
$var wire 1 h B $end
$var wire 1 d Y $end
$upscope $end
$scope module _061_ $end
$var wire 1 d A $end
$var wire 1 f B $end
$var wire 1 c Y $end
$upscope $end
$scope module _062_ $end
$var wire 1 c A $end
$var wire 1 j B $end
$var wire 1 m Y $end
$upscope $end
$scope module _063_ $end
$var wire 1 n A $end
$var wire 1 b Y $end
$upscope $end
$scope module _064_ $end
$var wire 1 g A $end
$var wire 1 b B $end
$var wire 1 a Y $end
$upscope $end
$scope module _065_ $end
$var wire 1 o A $end
$var wire 1 ` Y $end
$upscope $end
$scope module _066_ $end
$var wire 1 ` A $end
$var wire 1 h B $end
$var wire 1 _ Y $end
$upscope $end
$scope module _067_ $end
$var wire 1 _ A $end
$var wire 1 a B $end
$var wire 1 ^ Y $end
$upscope $end
$scope module _068_ $end
$var wire 1 ^ A $end
$var wire 1 j B $end
$var wire 1 p Y $end
$upscope $end
$scope module _069_ $end
$var wire 1 q A $end
$var wire 1 ] Y $end
$upscope $end
$scope module _070_ $end
$var wire 1 g A $end
$var wire 1 ] B $end
$var wire 1 \ Y $end
$upscope $end
$scope module _071_ $end
$var wire 1 r A $end
$var wire 1 [ Y $end
$upscope $end
$scope module _072_ $end
$var wire 1 [ A $end
$var wire 1 h B $end
$var wire 1 Z Y $end
$upscope $end
$scope module _073_ $end
$var wire 1 Z A $end
$var wire 1 \ B $end
$var wire 1 Y Y $end
$upscope $end
$scope module _074_ $end
$var wire 1 Y A $end
$var wire 1 j B $end
$var wire 1 s Y $end
$upscope $end
$scope module _075_ $end
$var wire 1 t A $end
$var wire 1 X Y $end
$upscope $end
$scope module _076_ $end
$var wire 1 g A $end
$var wire 1 X B $end
$var wire 1 W Y $end
$upscope $end
$scope module _077_ $end
$var wire 1 u A $end
$var wire 1 V Y $end
$upscope $end
$scope module _078_ $end
$var wire 1 V A $end
$var wire 1 h B $end
$var wire 1 U Y $end
$upscope $end
$scope module _079_ $end
$var wire 1 U A $end
$var wire 1 W B $end
$var wire 1 T Y $end
$upscope $end
$scope module _080_ $end
$var wire 1 T A $end
$var wire 1 j B $end
$var wire 1 v Y $end
$upscope $end
$scope module _081_ $end
$var wire 1 w A $end
$var wire 1 S Y $end
$upscope $end
$scope module _082_ $end
$var wire 1 g A $end
$var wire 1 S B $end
$var wire 1 R Y $end
$upscope $end
$scope module _083_ $end
$var wire 1 x A $end
$var wire 1 Q Y $end
$upscope $end
$scope module _084_ $end
$var wire 1 Q A $end
$var wire 1 h B $end
$var wire 1 P Y $end
$upscope $end
$scope module _085_ $end
$var wire 1 P A $end
$var wire 1 R B $end
$var wire 1 O Y $end
$upscope $end
$scope module _086_ $end
$var wire 1 O A $end
$var wire 1 j B $end
$var wire 1 y Y $end
$upscope $end
$scope module _087_ $end
$var wire 1 z A $end
$var wire 1 N Y $end
$upscope $end
$scope module _088_ $end
$var wire 1 g A $end
$var wire 1 N B $end
$var wire 1 M Y $end
$upscope $end
$scope module _089_ $end
$var wire 1 { A $end
$var wire 1 L Y $end
$upscope $end
$scope module _090_ $end
$var wire 1 L A $end
$var wire 1 h B $end
$var wire 1 K Y $end
$upscope $end
$scope module _091_ $end
$var wire 1 K A $end
$var wire 1 M B $end
$var wire 1 J Y $end
$upscope $end
$scope module _092_ $end
$var wire 1 J A $end
$var wire 1 j B $end
$var wire 1 | Y $end
$upscope $end
$scope module _093_ $end
$var wire 1 } A $end
$var wire 1 I Y $end
$upscope $end
$scope module _094_ $end
$var wire 1 g A $end
$var wire 1 I B $end
$var wire 1 H Y $end
$upscope $end
$scope module _095_ $end
$var wire 1 ~ A $end
$var wire 1 G Y $end
$upscope $end
$scope module _096_ $end
$var wire 1 G A $end
$var wire 1 h B $end
$var wire 1 F Y $end
$upscope $end
$scope module _097_ $end
$var wire 1 F A $end
$var wire 1 H B $end
$var wire 1 E Y $end
$upscope $end
$scope module _098_ $end
$var wire 1 E A $end
$var wire 1 j B $end
$var wire 1 !" Y $end
$upscope $end
$scope module _099_ $end
$var wire 1 "" A $end
$var wire 1 D Y $end
$upscope $end
$scope module _100_ $end
$var wire 1 g A $end
$var wire 1 D B $end
$var wire 1 C Y $end
$upscope $end
$scope module _101_ $end
$var wire 1 #" A $end
$var wire 1 B Y $end
$upscope $end
$scope module _102_ $end
$var wire 1 B A $end
$var wire 1 h B $end
$var wire 1 A Y $end
$upscope $end
$scope module _103_ $end
$var wire 1 A A $end
$var wire 1 C B $end
$var wire 1 @ Y $end
$upscope $end
$scope module _104_ $end
$var wire 1 @ A $end
$var wire 1 j B $end
$var wire 1 $" Y $end
$upscope $end
$scope module _105_ $end
$var wire 1 %" A $end
$var wire 1 ? Y $end
$upscope $end
$scope module _106_ $end
$var wire 1 g A $end
$var wire 1 ? B $end
$var wire 1 > Y $end
$upscope $end
$scope module _107_ $end
$var wire 1 &" A $end
$var wire 1 = Y $end
$upscope $end
$scope module _108_ $end
$var wire 1 = A $end
$var wire 1 h B $end
$var wire 1 < Y $end
$upscope $end
$scope module _109_ $end
$var wire 1 < A $end
$var wire 1 > B $end
$var wire 1 ; Y $end
$upscope $end
$scope module _110_ $end
$var wire 1 ; A $end
$var wire 1 j B $end
$var wire 1 '" Y $end
$upscope $end
$scope module _111_ $end
$var wire 1 (" A $end
$var wire 1 : Y $end
$upscope $end
$scope module _112_ $end
$var wire 1 g A $end
$var wire 1 : B $end
$var wire 1 9 Y $end
$upscope $end
$scope module _113_ $end
$var wire 1 )" A $end
$var wire 1 8 Y $end
$upscope $end
$scope module _114_ $end
$var wire 1 8 A $end
$var wire 1 h B $end
$var wire 1 7 Y $end
$upscope $end
$scope module _115_ $end
$var wire 1 7 A $end
$var wire 1 9 B $end
$var wire 1 6 Y $end
$upscope $end
$scope module _116_ $end
$var wire 1 6 A $end
$var wire 1 j B $end
$var wire 1 *" Y $end
$upscope $end
$scope module _117_ $end
$var wire 1 5 Y $end
$var wire 1 ' B $end
$var wire 1 & A $end
$upscope $end
$scope module _118_ $end
$var wire 1 5 A $end
$var wire 1 j B $end
$var wire 1 # Y $end
$upscope $end
$upscope $end
$scope module proba $end
$var wire 10 +" dataout_dest [9:0] $end
$var wire 10 ," dataout_destEst [9:0] $end
$var wire 1 $ validoutdest $end
$var wire 1 # validoutdestEst $end
$var reg 1 , clk $end
$var reg 10 -" datain_dest0 [9:0] $end
$var reg 10 ." datain_dest1 [9:0] $end
$var reg 1 ' pop0 $end
$var reg 1 & pop1 $end
$var reg 1 % reset_L $end
$upscope $end
$upscope $end
$scope module DFF $end
$var wire 1 /" C $end
$var wire 1 0" D $end
$var reg 1 1" Q $end
$upscope $end
$scope module DFFSR $end
$var wire 1 2" C $end
$var wire 1 3" D $end
$var wire 1 4" R $end
$var wire 1 5" S $end
$var reg 1 6" Q $end
$upscope $end
$enddefinitions $end
#0
$dumpvars
x6"
z5"
z4"
z3"
z2"
x1"
z0"
z/"
b0 ."
b0 -"
b0 ,"
b0 +"
0*"
0)"
0("
0'"
0&"
0%"
0$"
0#"
0""
0!"
0~
0}
0|
0{
0z
0y
0x
0w
0v
0u
0t
0s
0r
0q
0p
0o
0n
0m
0l
0k
1j
1i
1h
1g
0f
1e
0d
1c
1b
0a
1`
0_
1^
1]
0\
1[
0Z
1Y
1X
0W
1V
0U
1T
1S
0R
1Q
0P
1O
1N
0M
1L
0K
1J
1I
0H
1G
0F
1E
1D
0C
1B
0A
1@
1?
0>
1=
0<
1;
1:
09
18
07
16
15
b0 4
b0 3
b0 2
01
b0 0
b0 /
b0 .
b0 -
0,
b0 +
b0 *
b0 )
b0 (
0'
0&
0%
0$
0#
z"
z!
$end
#1000
0j
1%
1,
#2000
0,
#3000
1$
b111000010 )
b111000010 /
b111000010 +"
1'"
1$"
1!"
b111000010 (
b111000010 2
b111000010 ,"
1p
0;
0@
0E
0^
1<
1A
1F
1_
1#
0I
0b
0=
0B
0G
0`
05
1}
1n
1&"
1#"
1~
1o
0h
b111000010 0
11
b1000010 *
b1000010 -
b1000010 3
b1000010 ."
b111000010 +
b111000010 .
b111000010 4
b111000010 -"
1'
1,
#4000
0,
#5000
b1000111110 )
b1000111110 /
b1000111110 +"
1s
1v
1y
1|
1*"
1p
0!"
0$"
b1000111110 (
b1000111110 2
b1000111110 ,"
0'"
0Y
0T
0O
0J
06
0^
1E
1@
1;
1a
1\
1W
1R
1M
19
0_
0F
0A
0<
0:
1I
0N
0S
0X
0]
1B
0Q
0e
0g
1("
0}
1z
1w
1t
1q
0#"
1x
1l
1h
11
b1000111110 0
b1000111110 *
b1000111110 -
b1000111110 3
b1000111110 ."
b101010011 +
b101010011 .
b101010011 4
b101010011 -"
1&
0'
1,
#6000
0,
#7000
b1001110110 )
b1001110110 /
b1001110110 +"
0v
0m
1!"
b1001110110 (
b1001110110 2
b1001110110 ,"
0'"
1T
1c
0E
1;
17
1K
1Z
0a
0\
0W
0R
0M
09
0d
1_
1P
1F
0<
1:
0?
0I
1N
1S
1]
1b
0i
08
1=
0L
0[
1e
1g
0("
1%"
1}
0z
0w
0q
0n
1k
1)"
0&"
1{
1r
0l
0h
11
b1001110110 0
b101001001 *
b101001001 -
b101001001 3
b101001001 ."
b1001110110 +
b1001110110 .
b1001110110 4
b1001110110 -"
0&
1'
1,
#8000
0,
#9000
b1101000011 )
b1101000011 /
b1101000011 +"
1m
1'"
1p
0s
0y
0|
1!"
b1101000011 (
b1101000011 2
b1101000011 ,"
1*"
0c
0;
0^
1Y
1O
1J
0E
06
1f
1a
1H
1>
19
0_
0Z
0P
0K
0F
07
0:
1X
0b
18
1Q
0V
1`
0e
0g
1("
0t
1n
0)"
0x
1u
0o
1l
1h
11
b1101000011 0
b1101000011 *
b1101000011 -
b1101000011 3
b1101000011 ."
b1101101 +
b1101101 .
b1101101 4
b1101101 -"
1&
0'
1,
#10000
0,
#11000
0$
b0 )
b0 /
b0 +"
0m
0p
0!"
0'"
b0 (
b0 2
b0 ,"
0*"
1c
1^
1E
1;
16
0#
0f
0a
0H
0>
09
1?
1I
0N
0S
0X
0]
1i
0=
1L
0Q
1V
1[
0`
1e
15
1g
0%"
0}
1z
1w
1t
1q
0k
1&"
0{
1x
0u
0r
1o
0l
01
b0 0
b1000111110 *
b1000111110 -
b1000111110 3
b1000111110 ."
b101010010 +
b101010010 .
b101010010 4
b101010010 -"
0&
1,
#12000
0,
#13000
0D
0I
1N
1S
1X
1]
0B
1Q
1""
1}
0z
0w
0t
0q
1#"
0x
b1011000010 *
b1011000010 -
b1011000010 3
b1011000010 ."
b111000010 +
b111000010 .
b111000010 4
b111000010 -"
1,
#14000
0,
#15000
0S
1b
08
1G
0[
1`
0e
1w
0n
1)"
0~
1r
0o
1l
b1011010000 *
b1011010000 -
b1011010000 3
b1011010000 ."
b1110000101 +
b1110000101 .
b1110000101 4
b1110000101 -"
1,
#16000
0,
#17000
1:
0?
1D
0X
0b
0G
0L
0Q
0V
0`
1e
0("
1%"
0""
1t
1n
1~
1{
1x
1u
1o
0l
b101011010 *
b101011010 -
b101011010 3
b101011010 ."
b1111111110 +
b1111111110 .
b1111111110 4
b1111111110 -"
1,
#18000
0,
#19000
1$
b1000111110 )
b1000111110 /
b1000111110 +"
1p
1s
1v
1y
1|
0!"
0$"
0'"
b1000111110 (
b1000111110 2
b1000111110 ,"
1*"
0^
0Y
0T
0O
0J
1E
1@
1;
06
1#
1_
1Z
1U
1P
1K
0F
0A
0<
17
0:
0D
1I
0N
0]
1=
1B
1G
05
1("
1""
0}
1z
1q
0&"
0#"
0~
0h
b1000111110 0
11
b1110111110 *
b1110111110 -
b1110111110 3
b1110111110 ."
b1000111110 +
b1000111110 .
b1000111110 4
b1000111110 -"
1&
1'
1,
#20000
0,
#21000
b1011111010 )
b1011111010 /
b1011111010 +"
1$"
1!"
b1011111010 (
b1011111010 2
b1011111010 ,"
0s
0@
0E
1Y
1A
1F
0Z
1:
1D
0I
1N
1X
1]
0B
0G
1[
0("
0""
1}
0z
0t
0q
1#"
1~
0r
11
b1011111010 0
b101010010 *
b101010010 -
b101010010 3
b101010010 ."
b1011111010 +
b1011111010 .
b1011111010 4
b1011111010 -"
1,
#22000
0,
#23000
b1000110101 )
b1000110101 /
b1000110101 +"
0$"
0!"
0v
1s
0p
b1000110101 (
b1000110101 2
b1000110101 ,"
1m
1@
1E
1T
0Y
1^
0c
0A
0F
0U
1Z
0_
1d
0:
1?
1I
0N
0X
0]
1B
1G
1V
0[
1`
0e
1("
0%"
0}
1z
1t
1q
0#"
0~
0u
1r
0o
1l
11
b1000110101 0
b1000111110 *
b1000111110 -
b1000111110 3
b1000111110 ."
b1000110101 +
b1000110101 .
b1000110101 4
b1000110101 -"
1,
#24000
0,
#25000
b1000111110 )
b1000111110 /
b1000111110 +"
1p
1v
0^
0T
0m
1s
1y
1|
b1000111110 (
b1000111110 2
b1000111110 ,"
1*"
1a
1\
1W
1R
1M
19
1c
0Y
0O
0J
06
0g
0d
0Z
0P
0K
07
1h
11
b1000111110 0
0'
1,
#26000
0,
#27000
b111000111 )
b111000111 /
b111000111 +"
0*"
1'"
1$"
1!"
0|
0y
0v
b111000111 (
b111000111 2
b111000111 ,"
1m
16
0;
0@
0E
1J
1O
1T
0c
09
1>
1C
1H
0M
0R
0W
1f
1:
0?
0D
0I
1N
1S
1X
0i
0("
1%"
1""
1}
0z
0w
0t
1k
11
b111000111 0
b111000111 *
b111000111 -
b111000111 3
b111000111 ."
1,
